.pydevproject
CHANGES.txt
Contributors.txt
LICENSE.txt
README.txt
setup.cfg
setup.py
.settings/org.eclipse.core.resources.prefs
ListComparator.egg-info/PKG-INFO
ListComparator.egg-info/SOURCES.txt
ListComparator.egg-info/dependency_links.txt
ListComparator.egg-info/entry_points.txt
ListComparator.egg-info/requires.txt
ListComparator.egg-info/top_level.txt
ListComparator.egg-info/zip-safe
listcomparator/__init__.py
listcomparator/comparator.py
listcomparator/csv_cmp.py
listcomparator/csv_cmp_diff.py
listcomparator/xml_cmp.py
listcomparator/tests/__init__.py
listcomparator/tests/test_comparator.py
listcomparator/tests/test_doctests.py