Metadata-Version: 1.0
Name: ListComparator
Version: 0.1
Summary: Compares ordered lists, xml and csv application
Home-page: http://code.google.com/p/listcomparator/
Author: Nicolas Laurance
Author-email: nlaurance at zindep dot com
License: GPL
Keywords: xml csv list compare diff difference
Platform: UNKNOWN
Classifier: Development Status :: 5 - Production/Stable
Classifier: Intended Audience :: Developers
Classifier: License :: OSI Approved :: GNU General Public License (GPL)
Classifier: Operating System :: OS Independent
Classifier: Programming Language :: Python
Classifier: Topic :: Software Development :: Libraries :: Python Modules
Classifier: Topic :: Text Processing :: Filters
Classifier: Topic :: Text Processing :: Markup :: XML
Classifier: Topic :: Utilities
